setup.py
commonchi.egg-info/PKG-INFO
commonchi.egg-info/SOURCES.txt
commonchi.egg-info/dependency_links.txt
commonchi.egg-info/requires.txt
commonchi.egg-info/top_level.txt
commonchi/lib/Context.py
commonchi/lib/ReplaceVariable.py
commonchi/lib/__init__.py
commonchi/lib/api.py
commonchi/lib/newReport.py
commonchi/lib/public.py
commonchi/lib/readexcel.py
commonchi/lib/sendmail.py
commonchi/lib/sendrequests.py
commonchi/lib/utility.py
commonchi/lib/writeexcel.py
commonchi/package/HTMLTestRunner.py
commonchi/package/__init__.py