Metadata-Version: 1.0
Name: commonchi
Version: 4.0.0
Summary: commonchi
Home-page: UNKNOWN
Author: cxx
Author-email: cuixiaoxia@chinasofti.com
License: UNKNOWN
Platform: UNKNOWN
